{
    "j": [
        {
            "palavra": "JUROU-LHE",
            "veja tambem": [
                "jurar"
            ],
            "ocorrencias": 4,
            "fonte": "",
            "concordancias": [
                {
                    "referencia": "Gênesis 24.9",
                    "texto": "coxa de Abraão, seu senhor, e J, sobre este negócio."
                },
                {
                    "referencia": "Gênesis 25.33",
                    "texto": "disse Jacó: Jura-me hoje. E J, e vendeu a"
                },
                {
                    "referencia": "Gênesis 47.31",
                    "texto": "E disse ele: Jura-me. E ele J.; e Israel"
                },
                {
                    "referencia": "Marcos 6.23",
                    "texto": "E J., dizendo: Tudo o que me pedires te darei,"
                }
            ]
        },
        {
            "palavra": "JUSABE-HESEDE",
            "veja tambem": [],
            "ocorrencias": 1,
            "fonte": "",
            "concordancias": [
                {
                    "referencia": "1 Crônicas 3.20",
                    "texto": "e Berequias, e Hasadias, e J.; cinco"
                }
            ]
        },
        {
            "palavra": "JUSTA",
            "veja tambem": [
                "justo"
            ],
            "ocorrencias": 11,
            "fonte": "",
            "concordancias": [
                {
                    "referencia": "Gênesis 20.4",
                    "texto": "isso, disse: Senhor, matarás também uma nação J.?"
                },
                {
                    "referencia": "Gênesis 38.26",
                    "texto": "Judá e disse: Mais J. é ela do que eu,"
                },
                {
                    "referencia": "Jó 6.29",
                    "texto": "iniquidade; voltai, sim, que a minha causa é J.."
                },
                {
                    "referencia": "Provérbios 16.11",
                    "texto": "O peso e a balança J. são do Senhor; obra sua são"
                },
                {
                    "referencia": "Isaías 26.2",
                    "texto": "para que entre nela a nação J., que observa a verdade."
                },
                {
                    "referencia": "Romanos 3.8",
                    "texto": "para que venham bens? A condenação desses é J.."
                },
                {
                    "referencia": "Efésios 4.16",
                    "texto": "todas as juntas, segundo a J. operação de cada"
                },
                {
                    "referencia": "1 Tessalonicenses 2.10",
                    "texto": "testemunhas de quão santa T. e"
                },
                {
                    "referencia": "Tito 2.12",
                    "texto": "vivamos neste presente século sóbria, J, e piamente,"
                },
                {
                    "referencia": "Hebreus 2.2",
                    "texto": "e desobediência recebeu a J. retribuição,"
                },
                {
                    "referencia": "2 Pedro 2.8",
                    "texto": "todos os dias a sua alma J., pelo que via e"
                }
            ]
        },
        {
            "palavra": "JUSTAMENTE",
            "veja tambem": [
                "justo"
            ],
            "ocorrencias": 9,
            "fonte": "",
            "concordancias": [
                {
                    "referencia": "Gênesis 27.36",
                    "texto": "ele: Não foi o seu nome J. chamado Jacó?"
                },
                {
                    "referencia": "Deuteronômio 1.16",
                    "texto": "entre vossos irmãos e julgai J. entre o"
                },
                {
                    "referencia": "S19.4",
                    "texto": "tu te assentaste no tribunal, julgando J.."
                },
                {
                    "referencia": "Provérbios 17.26",
                    "texto": "justo, nem ferirem os príncipes ao que age J.."
                },
                {
                    "referencia": "Isaías 49.24",
                    "texto": "a presa ao valente? Ou os presos J. escapariam?"
                },
                {
                    "referencia": "Jeremias 21.12",
                    "texto": "o Senhor: Julgai pela manhã J. e livrai o"
                },
                {
                    "referencia": "1 Coríntios 9.12",
                    "texto": "sobre vós, por que não, mais J., nós? Mas nós"
                },
                {
                    "referencia": "1 Coríntios 15.34",
                    "texto": "Vigiai J. e não pequeis; porque alguns ainda"
                },
                {
                    "referencia": "1 Pedro 2.23",
                    "texto": "ameaçava, mas entregava-se àquele que julga J.,"
                }
            ]
        },
        {
            "palavra": "JUSTAS",
            "veja tambem": [
                "justo"
            ],
            "ocorrencias": 5,
            "fonte": "",
            "concordancias": [
                {
                    "referencia": "Levítico 19.36",
                    "texto": "Balanças J., pedras J., efa justo e justo him"
                },
                {
                    "referencia": "Provérbios 8.9",
                    "texto": "o que bem as entende e J., para os que acham"
                },
                {
                    "referencia": "Ezequiel 16.52",
                    "texto": "abomináveis do que elas; mais J. são do que"
                },
                {
                    "referencia": "Ezequiel 45.10",
                    "texto": "Balanças J., e efa justo, e bato justo tereis."
                },
                {
                    "referencia": "1 João 3.12",
                    "texto": "as suas obras eram más, e as de seu irmão, J.."
                }
            ]
        }
    ]
}