{
    "livro": "Salmos",
    "capitulo": 124,
    "titulos": {
        "1": "Cântico para os peregrinos a caminho de Jerusalém; salmo de Davi."
    },
    "versiculos": {
        "1": "E se o Senhor não estivesse ao nosso lado? Que todo o Israel diga:",
        "2": "E se o Senhor não estivesse ao nosso lado quando os inimigos nos atacaram?",
        "3": "Eles nos teriam engolido vivos com sua ira ardente contra nós.",
        "4": "As águas nos teriam encoberto, a correnteza nos teria afogado.",
        "5": "Sim, as águas violentas de sua fúria nos teriam afogado.",
        "6": "Louvado seja o Senhor, que não permitiu que nos despedaçassem com seus dentes!",
        "7": "Escapamos como um pássaro que foge da armadilha do caçador; a armadilha se quebrou, e estamos livres!",
        "8": "Nosso socorro vem do Senhor, que fez os céus e a terra."
    }
}