{
    "d": [
        {
            "palavra": "DIREIS",
            "veja tambem": [
                "dizer"
            ],
            "ocorrencias": 36,
            "fonte": "",
            "concordancias": [
                {
                    "referencia": "Gênesis 32.4",
                    "texto": "ordenou-lhes, dizendo: Assim D. a meu senhor"
                },
                {
                    "referencia": "Gênesis 32.20",
                    "texto": "E D. também: Eis que o teu servo Jacó vem atrás"
                },
                {
                    "referencia": "Gênesis 46.34",
                    "texto": "Então, D.: Teus servos foram homens de gado desde"
                },
                {
                    "referencia": "Gênesis 50.17",
                    "texto": "Assim D. a José: Perdoa, rogo-te, a transgressão"
                },
                {
                    "referencia": "Êxodo 12.27",
                    "texto": "Então, D.: Este é o sacrifício da Páscoa ao"
                },
                {
                    "referencia": "Josué 4.7",
                    "texto": "então, lhes D. que as águas do Jordão se"
                },
                {
                    "referencia": "Juízes 7.18",
                    "texto": "ao redor de todo o arraial e D.: Pelo Senhor e Gideão."
                },
                {
                    "referencia": "1 Samuel 11.9",
                    "texto": "que vieram: Assim D, aos homens de"
                },
                {
                    "referencia": "1 Samuel 18.25",
                    "texto": "Então, disse Saul: Assim D. a Davi: O rei não tem"
                },
                {
                    "referencia": "1 Samuel 25.6",
                    "texto": "E assim D. àquele próspero: Paz tenhas, e que a"
                },
                {
                    "referencia": "2 Samuel 15.10",
                    "texto": "ouvirdes o som das trombetas, D.: Absalão reina"
                },
                {
                    "referencia": "2 Samuel 19.13",
                    "texto": "E a Amasa D.: Porventura, não és tu meu osso e"
                },
                {
                    "referencia": "IRs 1.34",
                    "texto": "então, tocareis a trombeta e D.: Viva o rei Salomão!"
                },
                {
                    "referencia": "1 Reis 22.27",
                    "texto": "e D.: Assim diz o rei: Metei este homem na casa"
                },
                {
                    "referencia": "2 Reis 19.6",
                    "texto": "E Isaías lhes disse: Assim D. a vosso senhor:"
                },
                {
                    "referencia": "2 Reis 22.18",
                    "texto": "ao Senhor, assim lhe D.: Assim diz o"
                },
                {
                    "referencia": "2 Crônicas 34.26",
                    "texto": "ao Senhor, assim lhe D.: Assim diz o"
                },
                {
                    "referencia": "Jó 21.28",
                    "texto": "Porque D.: Onde está a casa do príncipe e onde a"
                },
                {
                    "referencia": "Isaías 37.6",
                    "texto": "E Isaías lhes disse: Assim D, a vosso amo: Assim"
                },
                {
                    "referencia": "Jeremias 7.10",
                    "texto": "que se chama pelo meu nome, e D.: Somos livres,"
                },
                {
                    "referencia": "Jeremias 10.11",
                    "texto": "Assim lhes D. : Os deuses que não fizeram os céus"
                },
                {
                    "referencia": "Jeremias 21.3",
                    "texto": "Então, Jeremias lhes disse: Assim D, a Zedequias."
                },
                {
                    "referencia": "Jeremias 23.35",
                    "texto": "Assim D., cada um ao seu companheiro e cada um ao"
                },
                {
                    "referencia": "Jeremias 23.38",
                    "texto": "(havendo-vos eu ordenado: não D., Peso do Senhor),"
                },
                {
                    "referencia": "Jeremias 27.4",
                    "texto": "o Deus de Israel: Assim D. a vossos senhores:"
                },
                {
                    "referencia": "Jeremias 37.7",
                    "texto": "Deus de Israel: Assim D. ao rei de Judá,"
                },
                {
                    "referencia": "Jeremias 48.14",
                    "texto": "Como D,: Somos valentes e homens fortes para guer-"
                },
                {
                    "referencia": "Jeremias 51.51",
                    "texto": "D.: Envergonhados estamos, porque ouvimos"
                },
                {
                    "referencia": "Ezequiel 18.3",
                    "texto": "Senhor Jeová, que nunca mais D. este provérbio em"
                },
                {
                    "referencia": "MI 1.5",
                    "texto": "os vossos olhos o verão, e D.: O Senhor seja"
                },
                {
                    "referencia": "Mateus 17.20",
                    "texto": "fé como um grão de mostarda, D. a este monte:"
                },
                {
                    "referencia": "Mateus 21.3",
                    "texto": "vos disser alguma coisa, D, que o Senhor"
                },
                {
                    "referencia": "Lucas 4.23",
                    "texto": "lhes disse: Sem dúvida, me D, este provérbio:"
                },
                {
                    "referencia": "Lucas 19.31",
                    "texto": "Por que o soltais?, assim lhe D.: Porque o Senhor"
                },
                {
                    "referencia": "Lucas 22.11",
                    "texto": "E D. ao pai de família da casa: O mestre te diz:"
                },
                {
                    "referencia": "Romanos 9.22",
                    "texto": "E que D, se Deus, querendo mostrar a sua ira e"
                }
            ]
        }
    ]
}