{
    "h": [
        {
            "palavra": "HABITÁ-LAS",
            "veja tambem": [
                "ha-"
            ],
            "ocorrencias": 1,
            "fonte": "",
            "concordancias": [
                {
                    "referencia": "Números 35.3",
                    "texto": "E terão estas cidades para H.; porém os seus"
                }
            ]
        },
        {
            "palavra": "HABITAÇOES",
            "veja tambem": [],
            "ocorrencias": 26,
            "fonte": "",
            "concordancias": [
                {
                    "referencia": "Gênesis 36.43",
                    "texto": "de Edom, segundo as suas H., na terra da"
                },
                {
                    "referencia": "Êxodo 10.23",
                    "texto": "os filhos de Israel tinham luz em suas H.."
                },
                {
                    "referencia": "Êxodo 12.20",
                    "texto": "em todas as vossas H. comereis pães asmos."
                },
                {
                    "referencia": "Levítico 3.17",
                    "texto": "em todas as vossas FL: nenhuma"
                },
                {
                    "referencia": "Levítico 7.26",
                    "texto": "em qualquer das vossas H., quer de aves"
                },
                {
                    "referencia": "Levítico 23.3",
                    "texto": "sábado do Senhor é em todas as vossas H.."
                },
                {
                    "referencia": "Levítico 23.14",
                    "texto": "é por vossas gerações, em todas as vossas M.."
                },
                {
                    "referencia": "Levítico 23.17",
                    "texto": "Das vossas FI, trareis dois pães de movimento;"
                },
                {
                    "referencia": "Levítico 23.21",
                    "texto": "perpétuo é em todas as vossas H. pelas"
                },
                {
                    "referencia": "Levítico 23.31",
                    "texto": "é pelas vossas gerações, em todas as vossas H.."
                },
                {
                    "referencia": "Números 15.2",
                    "texto": "na terra das vossas H., que eu vos"
                },
                {
                    "referencia": "Números 31.10",
                    "texto": "cidades com todas as suas H. e todos os seus acam-"
                },
                {
                    "referencia": "Números 35.29",
                    "texto": "a vossas gerações, em todas as vossas H.."
                },
                {
                    "referencia": "1 Crônicas 4.33",
                    "texto": "Baal, Estas foram as suas H. e suas genealogias."
                },
                {
                    "referencia": "1 Crônicas 441",
                    "texto": "de Judá, e feriram as tendas e H. dos que se"
                },
                {
                    "referencia": "1 Crônicas 6.54",
                    "texto": "E estas foram as suas H., segundo os seus"
                },
                {
                    "referencia": "S149.11",
                    "texto": "serão perpétuas, e as suas H., de geração em"
                },
                {
                    "referencia": "S155.15",
                    "texto": "porque há maldade nas suas Ħ. e no seu"
                },
                {
                    "referencia": "S178.28",
                    "texto": "no meio do seu arraial, ao redor de suas FL."
                },
                {
                    "referencia": "S183.12",
                    "texto": "possessão hereditária, as famosas FI. de Deus."
                },
                {
                    "referencia": "S187.2",
                    "texto": "portas de Sião mais do que todas as H, de Jacó."
                },
                {
                    "referencia": "Isaías 35.7",
                    "texto": "em mananciais de águas; e nas H, em que"
                },
                {
                    "referencia": "Isaías 54.2",
                    "texto": "eas cortinas das tuas H. se estendam;"
                },
                {
                    "referencia": "Ezequiel 6.14",
                    "texto": "de Ribla, em todas as suas H,; e saberão"
                },
                {
                    "referencia": "Ezequiel 34.13",
                    "texto": "junto às correntes e em todas as H. da terra."
                },
                {
                    "referencia": "Amós 1.2",
                    "texto": "dará a sua voz; nas H. dos pastores"
                }
            ]
        },
        {
            "palavra": "HABITADA",
            "veja tambem": [
                "habitar"
            ],
            "ocorrencias": 16,
            "fonte": "",
            "concordancias": [
                {
                    "referencia": "Êxodo 16.35",
                    "texto": "até que entraram em terra H.; comeram maná"
                },
                {
                    "referencia": "Isaías 13.20",
                    "texto": "Nunca mais será H., nem reedificada de geração"
                },
                {
                    "referencia": "Isaías 44.26",
                    "texto": "diz a Jerusalém: Tu serás H., e às cidades"
                },
                {
                    "referencia": "Isaías 45.18",
                    "texto": "mas a formou para que fosse H.: Eu sou o"
                },
                {
                    "referencia": "Jeremias 6.8",
                    "texto": "que não te torne em assolação e terra não H.."
                },
                {
                    "referencia": "Jeremias 17.25",
                    "texto": "de Jerusalém; e esta cidade será para sempre H.."
                },
                {
                    "referencia": "Jeremias 46.26",
                    "texto": "seus servos; mas, depois, será H. como nos"
                },
                {
                    "referencia": "Jeremias 50.13",
                    "texto": "furor do Senhor, não será H.; antes, se"
                },
                {
                    "referencia": "Jeremias 50.39",
                    "texto": "mais será povoada, nem será H, de geração"
                },
                {
                    "referencia": "Ezequiel 26.20",
                    "texto": "à cova, para que não sejas FL; e"
                },
                {
                    "referencia": "Ezequiel 29.11",
                    "texto": "passará por ela, nem será H. quarenta anos."
                },
                {
                    "referencia": "Zacarias 2.4",
                    "texto": "jovem, dizendo: Jerusalém será H. como as"
                },
                {
                    "referencia": "Ze 7.7",
                    "texto": "quando Jerusalém estava FI. e quieta, com as"
                },
                {
                    "referencia": "Zacarias 9.5",
                    "texto": "eo rei de Gaza perecerá, e Asquelom não será H.."
                },
                {
                    "referencia": "Zacarias 12.6",
                    "texto": "em redor, e Jerusalém será H. outra vez no"
                },
                {
                    "referencia": "Zacarias 14.10",
                    "texto": "ela será exalçada e H. no seu lugar,"
                }
            ]
        },
        {
            "palavra": "HABITADAS",
            "veja tambem": [
                "habitar"
            ],
            "ocorrencias": 6,
            "fonte": "",
            "concordancias": [
                {
                    "referencia": "Isaías 54.3",
                    "texto": "as nações e fará que sejam H. as cidades assoladas."
                },
                {
                    "referencia": "Ezequiel 12.20",
                    "texto": "E as cidades H. serão desoladas, e a terra se"
                },
                {
                    "referencia": "Ezequiel 35.9",
                    "texto": "cidades nunca mais serão H., assim"
                },
                {
                    "referencia": "Ezequiel 36.10",
                    "texto": "a toda ela; e as cidades serão H., eos"
                },
                {
                    "referencia": "Ezequiel 36.33",
                    "texto": "então, farei com que sejam H, as cidades e"
                },
                {
                    "referencia": "Ezequiel 36.35",
                    "texto": "assoladas, e destruídas estão fortalecidas e H.."
                }
            ]
        },
        {
            "palavra": "HABITADORES",
            "veja tambem": [],
            "ocorrencias": 1,
            "fonte": "",
            "concordancias": [
                {
                    "referencia": "1 Crônicas 9.2",
                    "texto": "E os primeiros H., que moravam nas suas"
                }
            ]
        }
    ]
}