{
    "l": [
        {
            "palavra": "LOUCOS",
            "veja tambem": [
                "louco"
            ],
            "ocorrencias": 23,
            "fonte": "",
            "concordancias": [
                {
                    "referencia": "2 Samuel 13.13",
                    "texto": "E tu serias como um dos L. de Israel. Agora,"
                },
                {
                    "referencia": "S15.5",
                    "texto": "Os L. não pararão à tua vista; aborreces a todos"
                },
                {
                    "referencia": "S139.8",
                    "texto": "transgressões; não me faças o opróbrio dos L.."
                },
                {
                    "referencia": "S175.4",
                    "texto": "Disse eu aos L.: não enlouqueçais; e aos ímpios:"
                },
                {
                    "referencia": "S194.8",
                    "texto": "brutais dentre o povo; e vós, L., quando sereis sábios?"
                },
                {
                    "referencia": "Provérbios 1.7",
                    "texto": "o princípio da ciência; os L. desprezam a"
                },
                {
                    "referencia": "Provérbios 1.22",
                    "texto": "desejareis o escárnio? E vós, L.,"
                },
                {
                    "referencia": "Provérbios 1.32",
                    "texto": "os matará, e a prosperidade dos L. os destruirá."
                },
                {
                    "referencia": "Provérbios 3.35",
                    "texto": "herdarão honra, mas os L. tomam sobre si confusão."
                },
                {
                    "referencia": "Provérbios 8.5",
                    "texto": "ó simples, a prudência; e vós, L., entendei de coração."
                },
                {
                    "referencia": "Provérbios 13.19",
                    "texto": "mas apartar-se do mal é abominação para os L.."
                },
                {
                    "referencia": "Provérbios 14.9",
                    "texto": "Os L. zombam do pecado, mas entre os retos há boa"
                },
                {
                    "referencia": "Isaías 19.11",
                    "texto": "Na verdade, L. são os príncipes de Zoã; o"
                },
                {
                    "referencia": "Isaías 19.13",
                    "texto": "L. se tornaram os príncipes de Zoã, e enganados"
                },
                {
                    "referencia": "Isaías 35.8",
                    "texto": "Deus; os caminhantes, até mesmo os L., não errarão."
                },
                {
                    "referencia": "Jeremias 5.4",
                    "texto": "estes são uns pobres; são L., pois não"
                },
                {
                    "referencia": "Jeremias 10.8",
                    "texto": "embruteceram e se tornaram L.; ensino de vaidades"
                },
                {
                    "referencia": "Ezequiel 13.3",
                    "texto": "Jeová: Ai dos profetas L., que seguem o seu"
                },
                {
                    "referencia": "Lucas 11.40",
                    "texto": "L. O que fez o exterior não fez também o interior?"
                },
                {
                    "referencia": "Romanos 1.22",
                    "texto": "Dizendo-se sábios, tornaram-se L.."
                },
                {
                    "referencia": "1 Coríntios 4.10",
                    "texto": "Nós somos L. por amor de Cristo, e vós, sábios em"
                },
                {
                    "referencia": "1 Coríntios 14.23",
                    "texto": "ou infiéis, não dirão, porventura, que estais L.?"
                },
                {
                    "referencia": "1 Pedro 2.15",
                    "texto": "o bem, tapeis a boca à ignorância dos homens L.;"
                }
            ]
        }
    ]
}